quickpip/__init__.py
quickpip/__main__.py
quickpip/compat.py
quickpip/quickpip.py
quickpip/utils.py
quickpip-0.0.4.dist-info/DESCRIPTION.rst
quickpip-0.0.4.dist-info/METADATA
quickpip-0.0.4.dist-info/RECORD
quickpip-0.0.4.dist-info/WHEEL
quickpip-0.0.4.dist-info/entry_points.txt
quickpip-0.0.4.dist-info/metadata.json
quickpip-0.0.4.dist-info/top_level.txt
